chunkhound/__init__.py
chunkhound/database.py
chunkhound/database_factory.py
chunkhound/embeddings.py
chunkhound/file_discovery_cache.py
chunkhound/llm_manager.py
chunkhound/parser.py
chunkhound/py.typed
chunkhound/tree_cache.py
chunkhound/version.py
chunkhound/api/__init__.py
chunkhound/api/cli/CLAUDE.md
chunkhound/api/cli/__init__.py
chunkhound/api/cli/env_detector.py
chunkhound/api/cli/keyboard.py
chunkhound/api/cli/main.py
chunkhound/api/cli/setup_wizard.py
chunkhound/api/cli/commands/__init__.py
chunkhound/api/cli/commands/calibrate.py
chunkhound/api/cli/commands/mcp.py
chunkhound/api/cli/commands/research.py
chunkhound/api/cli/commands/run.py
chunkhound/api/cli/commands/search.py
chunkhound/api/cli/parsers/__init__.py
chunkhound/api/cli/parsers/calibrate_parser.py
chunkhound/api/cli/parsers/common_arguments.py
chunkhound/api/cli/parsers/main_parser.py
chunkhound/api/cli/parsers/mcp_parser.py
chunkhound/api/cli/parsers/research_parser.py
chunkhound/api/cli/parsers/run_parser.py
chunkhound/api/cli/parsers/search_parser.py
chunkhound/api/cli/terminal/__init__.py
chunkhound/api/cli/terminal/core.py
chunkhound/api/cli/terminal/exceptions.py
chunkhound/api/cli/terminal/filters.py
chunkhound/api/cli/terminal/providers/__init__.py
chunkhound/api/cli/terminal/providers/base.py
chunkhound/api/cli/terminal/providers/unix.py
chunkhound/api/cli/terminal/providers/windows.py
chunkhound/api/cli/utils/__init__.py
chunkhound/api/cli/utils/config_factory.py
chunkhound/api/cli/utils/rich_output.py
chunkhound/api/cli/utils/text_input.py
chunkhound/api/cli/utils/tree_progress.py
chunkhound/api/cli/utils/validation.py
chunkhound/core/CLAUDE.md
chunkhound/core/__init__.py
chunkhound/core/constants.py
chunkhound/core/config/__init__.py
chunkhound/core/config/config.py
chunkhound/core/config/database_config.py
chunkhound/core/config/embedding_config.py
chunkhound/core/config/embedding_factory.py
chunkhound/core/config/indexing_config.py
chunkhound/core/config/llm_config.py
chunkhound-4.0.1.dist-info/METADATA
chunkhound-4.0.1.dist-info/WHEEL
chunkhound-4.0.1.dist-info/entry_points.txt
chunkhound-4.0.1.dist-info/licenses/LICENSE
chunkhound-4.0.1.dist-info/RECORD
