Metadata-Version: 2.4
Name: chunkhound
Version: 4.0.1
Summary: Local-first semantic code search with vector and regex capabilities for AI assistants via MCP
Project-URL: Homepage, https://github.com/chunkhound/chunkhound
Project-URL: Repository, https://github.com/chunkhound/chunkhound
Project-URL: Issues, https://github.com/chunkhound/chunkhound/issues
Project-URL: Documentation, https://github.com/chunkhound/chunkhound#readme
Project-URL: Changelog, https://github.com/chunkhound/chunkhound/releases
Author: Ofri Wolfus
License-File: LICENSE
Classifier: Development Status :: 3 - Alpha
Classifier: Environment :: Console
Classifier: Intended Audience :: Developers
Classifier: License :: OSI Approved :: MIT License
Classifier: Operating System :: OS Independent
Classifier: Programming Language :: Python :: 3
Classifier: Programming Language :: Python :: 3.10
Classifier: Programming Language :: Python :: 3.11
Classifier: Programming Language :: Python :: 3.12
Classifier: Programming Language :: Python :: 3.13
Classifier: Topic :: Internet :: WWW/HTTP :: Indexing/Search
Classifier: Topic :: Scientific/Engineering :: Artificial Intelligence
Classifier: Topic :: Software Development :: Code Generators
Classifier: Topic :: Software Development :: Libraries :: Python Modules
Classifier: Topic :: Text Processing :: Indexing
Requires-Python: <3.14,>=3.10
Requires-Dist: aiohttp>=3.12.15
Requires-Dist: duckdb>=1.4.0
Requires-Dist: fastmcp>=2.0.0
Requires-Dist: httpx>=0.28.1
Requires-Dist: lancedb>=0.25.2
Requires-Dist: loguru>=0.6.0
Requires-Dist: mcp>=1.0.0
Requires-Dist: numpy>=1.24.0
Requires-Dist: openai>=1.0.0
Requires-Dist: pandas>=2.3.0
Requires-Dist: pathspec>=0.12.1
Requires-Dist: psutil>=5.8.0
Requires-Dist: pydantic-settings>=2.0.0
Requires-Dist: pydantic>=2.11.0
Requires-Dist: pygit2>=1.12.0
Requires-Dist: pylance>=0.31.0
Requires-Dist: pymupdf>=1.23.0
Requires-Dist: pyyaml>=6.0.0
Requires-Dist: rapidyaml>=0.10.0
Requires-Dist: readchar>=4.2.1
Requires-Dist: rich>=13.0.0
Requires-Dist: scikit-learn>=1.3.0
Requires-Dist: tiktoken>=0.9.0
Requires-Dist: tree-sitter-bash>=0.25.0
Requires-Dist: tree-sitter-c>=0.24.1
Requires-Dist: tree-sitter-cpp>=0.23.4
Requires-Dist: tree-sitter-go>=0.25.0
Requires-Dist: tree-sitter-groovy>=0.1.2
Requires-Dist: tree-sitter-haskell>=0.23.1
Requires-Dist: tree-sitter-java>=0.23.5
Requires-Dist: tree-sitter-javascript>=0.25.0
Requires-Dist: tree-sitter-json>=0.24.8
Requires-Dist: tree-sitter-kotlin>=1.1.0
Requires-Dist: tree-sitter-language-pack>=0.7.3
Requires-Dist: tree-sitter-make>=0.1.0
Requires-Dist: tree-sitter-markdown>=0.5.1
Requires-Dist: tree-sitter-php>=0.24.0
Requires-Dist: tree-sitter-python>=0.25.0
Requires-Dist: tree-sitter-rust>=0.24.0
Requires-Dist: tree-sitter-toml>=0.7.0
Requires-Dist: tree-sitter-typescript>=0.23.2
Requires-Dist: tree-sitter-zig>=1.1.0
Requires-Dist: tree-sitter>=0.25.0
Requires-Dist: voyageai>=0.2.0
Requires-Dist: watchdog>=4.0.0
Requires-Dist: xxhash>=3.0.0
Provides-Extra: dev
Requires-Dist: black>=23.0.0; extra == 'dev'
Requires-Dist: mypy>=1.6.0; extra == 'dev'
Requires-Dist: pytest-asyncio>=0.21.0; extra == 'dev'
Requires-Dist: pytest-timeout>=2.1.0; extra == 'dev'
Requires-Dist: pytest>=7.4.0; extra == 'dev'
Requires-Dist: ruff>=0.1.0; extra == 'dev'
Provides-Extra: test
Requires-Dist: pytest-asyncio>=0.21.0; extra == 'test'
Requires-Dist: pytest-timeout>=2.1.0; extra == 'test'
Requires-Dist: pytest>=7.4.0; extra == 'test'
